cheech/__init__.py
cheech-0.2.0.dist-info/METADATA
cheech-0.2.0.dist-info/WHEEL
cheech-0.2.0.dist-info/RECORD
